uncensored/__init__.py
uncensored/_version.py
uncensored/api_config.py
uncensored/cli.py
uncensored/client.py
uncensored/completions.py
uncensored/exceptions.py
uncensored/files.py
uncensored/fine_tuning.py
uncensored/images.py
uncensored/models.py
uncensored/retries.py
uncensored/utils.py
uncensored-0.0.1.dist-info/LICENSE
uncensored-0.0.1.dist-info/METADATA
uncensored-0.0.1.dist-info/WHEEL
uncensored-0.0.1.dist-info/entry_points.txt
uncensored-0.0.1.dist-info/top_level.txt
uncensored-0.0.1.dist-info/RECORD
