Metadata-Version: 2.2
Name: uncensored
Version: 0.0.1
Summary: Official python library for the Uncensored AI (uncensored.com) API
Author-email: Uncensored AI <devs@uncensored.com>
License: MIT
Project-URL: Homepage, https://github.com/uncensored-com
Project-URL: Documentation, https://uncensored.com/docs
Project-URL: Repository, https://github.com/uncensored-com
Project-URL: Bug Tracker, https://github.com/uncensored-com
Keywords: ai,llm,uncensored,chat,image generation,fine-tuning
Classifier: Development Status :: 2 - Pre-Alpha
Classifier: Intended Audience :: Developers
Classifier: License :: OSI Approved :: MIT License
Classifier: Programming Language :: Python :: 3
Classifier: Programming Language :: Python :: 3.7
Classifier: Programming Language :: Python :: 3.8
Classifier: Programming Language :: Python :: 3.9
Classifier: Programming Language :: Python :: 3.10
Classifier: Topic :: Software Development :: Libraries :: Python Modules
Requires-Python: >=3.7
License-File: LICENSE
Requires-Dist: requests>=2.28.0
Requires-Dist: click>=8.0.0
